pacote_matrizes/__init__.py
pacote_matrizes/sum_column.py
pacote_matrizes/sum_row.py
pacote_matrizes-0.0.1.dist-info/METADATA
pacote_matrizes-0.0.1.dist-info/WHEEL
pacote_matrizes-0.0.1.dist-info/top_level.txt
pacote_matrizes-0.0.1.dist-info/RECORD
