Metadata-Version: 2.1
Name: pacote-matrizes
Version: 0.0.1
Summary: A package for summing rows and columns in Pandas DataFrames
Home-page: https://github.com/woodfabio/DIO-Criando-um-pacote-com-Python
Author: Fábio Wood
Author-email: fabio.wood.rs@gmail.com
Classifier: Programming Language :: Python :: 3
Classifier: License :: OSI Approved :: MIT License
Classifier: Operating System :: OS Independent
Requires-Python: >=3.6
Requires-Dist: pandas>=1.0
